yquoter/__init__.py
yquoter/cache.py
yquoter/config.py
yquoter/datasource.py
yquoter/exceptions.py
yquoter/indicators.py
yquoter/logger.py
yquoter/spider_core.py
yquoter/spider_source.py
yquoter/tushare_source.py
yquoter/utils.py
yquoter/configs/__init__.py
yquoter/configs/mapping.yaml
yquoter/configs/standard.yaml
yquoter-0.2.0.dist-info/licenses/LICENSE
yquoter-0.2.0.dist-info/METADATA
yquoter-0.2.0.dist-info/WHEEL
yquoter-0.2.0.dist-info/top_level.txt
yquoter-0.2.0.dist-info/RECORD
